odoo10_addon_hr_attendance_report_theoretical_time-10.0.2.0.0-nspkg.pth
odoo/addons/hr_attendance_report_theoretical_time/README.rst
odoo/addons/hr_attendance_report_theoretical_time/__init__.py
odoo/addons/hr_attendance_report_theoretical_time/__manifest__.py
odoo/addons/hr_attendance_report_theoretical_time/i18n/de.po
odoo/addons/hr_attendance_report_theoretical_time/i18n/es.po
odoo/addons/hr_attendance_report_theoretical_time/i18n/hr_attendance_report_theoretical_time.pot
odoo/addons/hr_attendance_report_theoretical_time/models/__init__.py
odoo/addons/hr_attendance_report_theoretical_time/models/hr_attendance.py
odoo/addons/hr_attendance_report_theoretical_time/models/hr_employee.py
odoo/addons/hr_attendance_report_theoretical_time/models/hr_holidays.py
odoo/addons/hr_attendance_report_theoretical_time/models/hr_holidays_public.py
odoo/addons/hr_attendance_report_theoretical_time/models/hr_holidays_status.py
odoo/addons/hr_attendance_report_theoretical_time/readme/CONFIGURE.rst
odoo/addons/hr_attendance_report_theoretical_time/readme/CONTRIBUTORS.rst
odoo/addons/hr_attendance_report_theoretical_time/readme/CREDITS.rst
odoo/addons/hr_attendance_report_theoretical_time/readme/DESCRIPTION.rst
odoo/addons/hr_attendance_report_theoretical_time/readme/INSTALL.rst
odoo/addons/hr_attendance_report_theoretical_time/readme/ROADMAP.rst
odoo/addons/hr_attendance_report_theoretical_time/readme/USAGE.rst
odoo/addons/hr_attendance_report_theoretical_time/reports/__init__.py
odoo/addons/hr_attendance_report_theoretical_time/reports/hr_attendance_theoretical_time_report.py
odoo/addons/hr_attendance_report_theoretical_time/reports/hr_attendance_theoretical_time_report_views.xml
odoo/addons/hr_attendance_report_theoretical_time/security/hr_attendance_report_theoretical_time_security.xml
odoo/addons/hr_attendance_report_theoretical_time/security/ir.model.access.csv
odoo/addons/hr_attendance_report_theoretical_time/static/description/icon.png
odoo10_addon_hr_attendance_report_theoretical_time-10.0.2.0.0.dist-info/METADATA
odoo10_addon_hr_attendance_report_theoretical_time-10.0.2.0.0.dist-info/WHEEL
odoo10_addon_hr_attendance_report_theoretical_time-10.0.2.0.0.dist-info/namespace_packages.txt
odoo10_addon_hr_attendance_report_theoretical_time-10.0.2.0.0.dist-info/top_level.txt
odoo10_addon_hr_attendance_report_theoretical_time-10.0.2.0.0.dist-info/RECORD
