Metadata-Version: 2.1
Name: odoo10-addon-hr-attendance-report-theoretical-time
Version: 10.0.2.0.0
Summary: Theoretical vs Attended Time Analysis
Home-page: https://github.com/OCA/hr
Author: Tecnativa, Odoo Community Association (OCA)
Author-email: support@odoo-community.org
License: AGPL-3
Platform: UNKNOWN
Classifier: Programming Language :: Python
Classifier: Framework :: Odoo
Classifier: License :: OSI Approved :: GNU Affero General Public License v3
Requires-Python: ~=2.7
Requires-Dist: odoo10-addon-hr-holidays-compute-days
Requires-Dist: odoo (<10.1dev,>=10.0)
